kolombo/__init__.py
kolombo/conf.py
kolombo/configuration_files.py
kolombo/console.py
kolombo/dkim.py
kolombo/domain.py
kolombo/init.py
kolombo/models.py
kolombo/py.typed
kolombo/run.py
kolombo/stop.py
kolombo/user.py
kolombo/util.py
kolombo/auth/__init__.py
kolombo/auth/_resolver.py
kolombo/auth/api.py
kolombo/auth/credentials.py
kolombo/auth/endpoints.py
kolombo/auth/protocol.py
kolombo/bin/__init__.py
kolombo/docker/Dockerfile.auth
kolombo/docker/Dockerfile.dkim-gen
kolombo/docker/Dockerfile.nginx
kolombo/docker/Dockerfile.receiver
kolombo/docker/Dockerfile.sender
kolombo/docker/auth/requirements.txt
kolombo/docker/auth/run_auth_api.sh
kolombo/docker/dkim-gen/gen_key.sh
kolombo/docker/nginx/nginx.conf
kolombo/docker/receiver/checkpassword.sh
kolombo/docker/receiver/dovecot.conf
kolombo/docker/receiver/postfix.conf
kolombo/docker/receiver/rsyslog.conf
kolombo/docker/receiver/start_receiver.sh
kolombo/docker/receiver/update_map.sh
kolombo/docker/sender/opendkim.conf
kolombo/docker/sender/postfix.conf
kolombo/docker/sender/rsyslog.conf
kolombo/docker/sender/start_sender.sh
kolombo/docker/services/docker-compose.yml
kolombo-0.5.0.dist-info/LICENSE
kolombo-0.5.0.dist-info/METADATA
kolombo-0.5.0.dist-info/WHEEL
kolombo-0.5.0.dist-info/entry_points.txt
kolombo-0.5.0.dist-info/top_level.txt
kolombo-0.5.0.dist-info/RECORD
