Metadata-Version: 2.1
Name: kolombo
Version: 0.5.0
Summary: Kolombo - CLI for easy mail server managing 💌
Home-page: https://github.com/HarrySky/kolombo
Author: Igor Nehoroshev
Author-email: hi@neigor.me
Maintainer: Igor Nehoroshev
Maintainer-email: hi@neigor.me
License: Apache License 2.0
Project-URL: Documentation, https://docs.neigor.me/kolombo
Project-URL: Changelog, https://github/HarrySky/kolombo/blob/main/README.md
Project-URL: Source, https://github.com/HarrySky/kolombo
Project-URL: Tracker, https://github.com/HarrySky/kolombo/issues
Platform: UNKNOWN
Classifier: Development Status :: 4 - Beta
Classifier: Intended Audience :: Developers
Classifier: Intended Audience :: System Administrators
Classifier: Intended Audience :: Information Technology
Classifier: License :: OSI Approved :: Apache Software License
Classifier: Operating System :: POSIX :: Linux
Classifier: Programming Language :: Python :: 3 :: Only
Classifier: Programming Language :: Python :: 3.8
Classifier: Programming Language :: Python :: 3.9
Classifier: Topic :: Communications :: Email
Classifier: Typing :: Typed
Requires-Python: >=3.8
Requires-Dist: aiosqlite (==0.17.0)
Requires-Dist: click (==8.0.1)
Requires-Dist: cryptography (==3.4.8)
Requires-Dist: databases (==0.5.2)
Requires-Dist: docker (==5.0.2)
Requires-Dist: ormar (==0.10.19)
Requires-Dist: rich (==10.10.0)
Requires-Dist: shellingham (==1.4.0)
Requires-Dist: typer (==0.4.0)
Requires-Dist: importlib-resources (==5.2.2) ; python_version < "3.9"
